moapi/__init__.py
moapi/adapters/__init__.py
moapi/adapters/query_string.py
moapi/mocks/__init__.py
moapi/mocks/connection/__init__.py
moapi/mocks/connection/mongo_parameters.py
moapi/models/__init__.py
moapi/models/core/__init__.py
moapi/models/core/custom_pydantic_fields.py
moapi/models/core/entity.py
moapi/moql/__init__.py
moapi/moql/casters.py
moapi/moql/constants.py
moapi/moql/core.py
moapi/moql/date_parser.py
moapi/moql/errors.py
moapi/moql/filter_handler.py
moapi/moql/limit_skip_handler.py
moapi/moql/operator_mapping.py
moapi/moql/projection_handler.py
moapi/moql/regex_parser.py
moapi/moql/sort_handler.py
moapi/moql/text_search_handler.py
moapi/moql/type_mapping.py
moapi/odm/__init__.py
moapi/odm/connection.py
moapi/odm/entity_service.py
moapi-1.1.0.dist-info/METADATA
moapi-1.1.0.dist-info/WHEEL
moapi-1.1.0.dist-info/RECORD
