Metadata-Version: 2.1
Name: moapi
Version: 1.1.0
Summary: Simple and lightweight Object-Document Mapper and simplified query syntax for query-string REST APIs
Author: Pedro Guzmán
Author-email: pedro.andres.guzman@ibm.com
Requires-Python: >=3.9,<4.0
Classifier: Programming Language :: Python :: 3
Classifier: Programming Language :: Python :: 3.9
Classifier: Programming Language :: Python :: 3.10
Classifier: Programming Language :: Python :: 3.11
Classifier: Programming Language :: Python :: 3.12
Classifier: Programming Language :: Python :: 3.13
Requires-Dist: confite (>=1.0.4,<2.0.0)
Requires-Dist: dateparser (>=1.2.0,<2.0.0)
Requires-Dist: email-validator (>=2.1.0.post1,<3.0.0)
Requires-Dist: pydantic[email] (>=2.4.2,<3.0.0)
Requires-Dist: pymongo (>=4.5.0,<5.0.0)
Requires-Dist: pynacl (>=1.5.0,<2.0.0)
Requires-Dist: setuptools (>=70.0.0,<71.0.0)
Requires-Dist: typer (>=0.9.0,<0.10.0)
